ptandroid/__init__.py
ptandroid/ptandroid.py
ptandroid/utils/__init__.py
ptandroid/utils/apktool.jar
ptandroid-0.0.4.dist-info/LICENSE
ptandroid-0.0.4.dist-info/METADATA
ptandroid-0.0.4.dist-info/WHEEL
ptandroid-0.0.4.dist-info/entry_points.txt
ptandroid-0.0.4.dist-info/top_level.txt
ptandroid-0.0.4.dist-info/RECORD
