Metadata-Version: 2.1
Name: ptandroid
Version: 0.0.4
Summary: APK/AXML Data Parser
Home-page: https://www.penterep.com/
Author: Penterep
Author-email: info@penterep.com
License: GPLv3+
Platform: UNKNOWN
Classifier: Programming Language :: Python :: 3.6
Classifier: Programming Language :: Python :: 3.7
Classifier: Environment :: Console
Requires-Python: >=3.6
License-File: LICENSE
Requires-Dist: androguard
Requires-Dist: defusedxml
Requires-Dist: ptlibs
